{
  "main": {
    "id": "24316818f8c5dd26",
    "type": "split",
    "children": [
      {
        "id": "095876706be9bdb7",
        "type": "tabs",
        "children": [
          {
            "id": "58dfe6fd9ca5959e",
            "type": "leaf",
            "state": {
              "type": "markdown",
              "state": {
                "file": "_posts/2023-07-19-accessibility-testing-in.md",
                "mode": "source",
                "source": false
              },
              "icon": "lucide-file",
              "title": "2023-07-19-accessibility-testing-in"
            }
          }
        ]
      }
    ],
    "direction": "vertical"
  },
  "left": {
    "id": "5811e7887e0fbf33",
    "type": "split",
    "children": [
      {
        "id": "3d8c41540d44f681",
        "type": "tabs",
        "children": [
          {
            "id": "9913245582c53c02",
            "type": "leaf",
            "state": {
              "type": "file-explorer",
              "state": {
                "sortOrder": "alphabetical",
                "autoReveal": false
              },
              "icon": "lucide-folder-closed",
              "title": "Files"
            }
          },
          {
            "id": "a9c8fdc4985c8548",
            "type": "leaf",
            "state": {
              "type": "search",
              "state": {
                "query": "",
                "matchingCase": false,
                "explainSearch": false,
                "collapseAll": false,
                "extraContext": false,
                "sortOrder": "alphabetical"
              },
              "icon": "lucide-search",
              "title": "Search"
            }
          },
          {
            "id": "9b8971c0160c3681",
            "type": "leaf",
            "state": {
              "type": "bookmarks",
              "state": {},
              "icon": "lucide-bookmark",
              "title": "Bookmarks"
            }
          }
        ]
      }
    ],
    "direction": "horizontal",
    "width": 300
  },
  "right": {
    "id": "64f17afe57b5ae8f",
    "type": "split",
    "children": [
      {
        "id": "ad6b1c316de2d484",
        "type": "tabs",
        "children": [
          {
            "id": "ee2c6f7be80258ff",
            "type": "leaf",
            "state": {
              "type": "backlink",
              "state": {
                "file": "_posts/2023-07-19-accessibility-testing-in.md",
                "collapseAll": false,
                "extraContext": false,
                "sortOrder": "alphabetical",
                "showSearch": false,
                "searchQuery": "",
                "backlinkCollapsed": false,
                "unlinkedCollapsed": true
              },
              "icon": "links-coming-in",
              "title": "Backlinks for 2023-07-19-accessibility-testing-in"
            }
          },
          {
            "id": "abbdb240a39a8b81",
            "type": "leaf",
            "state": {
              "type": "outgoing-link",
              "state": {
                "file": "_posts/2023-07-19-accessibility-testing-in.md",
                "linksCollapsed": false,
                "unlinkedCollapsed": true
              },
              "icon": "links-going-out",
              "title": "Outgoing links from 2023-07-19-accessibility-testing-in"
            }
          },
          {
            "id": "bc2fc48c084a79a0",
            "type": "leaf",
            "state": {
              "type": "tag",
              "state": {
                "sortOrder": "frequency",
                "useHierarchy": true,
                "showSearch": false,
                "searchQuery": ""
              },
              "icon": "lucide-tags",
              "title": "Tags"
            }
          },
          {
            "id": "20bf4a72d868becf",
            "type": "leaf",
            "state": {
              "type": "outline",
              "state": {
                "file": "_posts/2023-07-19-accessibility-testing-in.md",
                "followCursor": false,
                "showSearch": false,
                "searchQuery": ""
              },
              "icon": "lucide-list",
              "title": "Outline of 2023-07-19-accessibility-testing-in"
            }
          }
        ]
      }
    ],
    "direction": "horizontal",
    "width": 300,
    "collapsed": true
  },
  "left-ribbon": {
    "hiddenItems": {
      "switcher:Open quick switcher": false,
      "graph:Open graph view": false,
      "canvas:Create new canvas": false,
      "daily-notes:Open today's daily note": false,
      "templates:Insert template": false,
      "command-palette:Open command palette": false
    }
  },
  "active": "58dfe6fd9ca5959e",
  "lastOpenFiles": [
    "_site/css/main.css.map",
    "_site/2023/07/19/accessibility-testing-in.html",
    "_site/2023/05/15/using-act-to.html",
    "_site/2023/01/31/expo-app-config.html",
    "_site/2023/01/14/notion-for-software.html",
    "_site/2023/01/02/mustread-books-for.html",
    "_site/2023/07/19",
    "_site/2023/05/15",
    "_site/2023/01/31",
    "_site/2023/01/14",
    "_site/2023/01/02",
    "_site/images/safari_settings.png",
    "_site/images/logo.png",
    "_site/images/fa6c5dfe53.png",
    "_site/images/f159196842.png",
    "_site/images/ec18f32904.jpg",
    "_site/images/e1d2ad7014.jpg",
    "_site/images/develop_menu.png",
    "_site/images/cloud.png",
    "_site/images/a97bedecb3.jpg",
    "_site/images/a37debf5ab.jpg",
    "_site/README.md",
    "_posts/2018-04-02-reading-list.md"
  ]
}